devtools_html_entities/__init__.py
devtools_html_entities-1.0.1.dist-info/METADATA
devtools_html_entities-1.0.1.dist-info/WHEEL
devtools_html_entities-1.0.1.dist-info/top_level.txt
devtools_html_entities-1.0.1.dist-info/RECORD
