Metadata-Version: 2.1
Name: devtools-html-entities
Version: 1.0.1
Summary: HTML entities encoder/decoder
Home-page: https://devtools.at/tools/html-entities
Author: DevTools.at
Author-email: hello@devtools.at
Project-URL: Homepage, https://devtools.at/tools/html-entities
Project-URL: Repository, https://github.com/devtools-at/html-entities
Classifier: Development Status :: 4 - Beta
Classifier: Intended Audience :: Developers
Classifier: License :: OSI Approved :: MIT License
Classifier: Programming Language :: Python :: 3
Requires-Python: >=3.8
